martiniglass/__init__.py
martiniglass/martiniglass.py
martiniglass/data/cg_bonds-v6.tcl
martiniglass/data/eigen.py
martiniglass/data/proteins.vmd
martiniglass/data/vis.vmd
martiniglass/src/__init__.py
martiniglass/src/cylinders_tcl.py
martiniglass/src/index_writer.py
martiniglass/src/molecule_editing.py
martiniglass/src/network_writer.py
martiniglass/src/output_file_append.py
martiniglass/src/system_reading.py
martiniglass/src/topology.py
martiniglass-1.1.3.dist-info/licenses/LICENSE
martiniglass-1.1.3.dist-info/METADATA
martiniglass-1.1.3.dist-info/WHEEL
martiniglass-1.1.3.dist-info/entry_points.txt
martiniglass-1.1.3.dist-info/top_level.txt
martiniglass-1.1.3.dist-info/RECORD
