Metadata-Version: 2.4
Name: MartiniGlass
Version: 1.1.3
Author-email: Christopher Brasnett <c.s.brasnett@rug.nl>
License: Apache 2.0
Project-URL: Documentation, https://martiniglass.readthedocs.io/en/latest/
Project-URL: Repository, https://github.com/Martini-Force-Field-Initiative/MartiniGlass
Project-URL: Homepage, https://github.com/Martini-Force-Field-Initiative/MartiniGlass
Keywords: molecular dynamics,martini
Requires-Python: >=3.8
License-File: LICENSE
Requires-Dist: pbr
Requires-Dist: vermouth>=0.9.6
Dynamic: license-file
